{
  "name": "t3x-mydashboard",
  "full_name": "netresearch/t3x-mydashboard",
  "url": "https://github.com/netresearch/t3x-mydashboard",
  "description": "TYPO3 MyDashboard extension with some fixes and new features for 6.2",
  "language": "PHP",
  "category": "typo3-extension",
  "license": null,
  "topics": [],
  "homepage": "http://typo3.org/extensions/repository/view/mydashboard",
  "default_branch": "master",
  "created_at": "2014-07-15T14:18:57Z",
  "pushed_at": "2014-11-11T13:30:47Z",
  "updated_at": "2023-11-23T14:01:52Z",
  "composer_name": null,
  "lifetime": {
    "stars": 0,
    "forks": 0,
    "watchers": 6,
    "network": 0,
    "open_issues_plus_prs": 0,
    "commits": 5,
    "issues_open": 0,
    "issues_closed": 0,
    "prs_open": 0,
    "prs_merged": 0,
    "prs_closed_unmerged": 0,
    "issues_total": 0,
    "releases": 0,
    "release_downloads": 0,
    "contributors": 0,
    "external_contributors": 0,
    "packagist_downloads": 0,
    "ghcr_downloads": 0,
    "dependents_repos": 0,
    "dependents_packages": 0
  },
  "recent_30d": {
    "commits": 0,
    "issues_opened": 0,
    "prs_opened": 0,
    "prs_merged": 0,
    "releases": 0,
    "packagist_downloads": 0,
    "ghcr_downloads": 0
  },
  "traffic_14d": {
    "clones_total": 28,
    "clones_unique": 27,
    "views_total": 0,
    "views_unique": 0,
    "top_referrers": [],
    "top_paths": []
  },
  "latest_release": null,
  "top_contributors": [],
  "packagist": null,
  "ghcr": null,
  "dependents": {
    "repositories": 0,
    "packages": 0,
    "url": "https://github.com/netresearch/t3x-mydashboard/network/dependents"
  },
  "blast_radius": 0,
  "archived": true
}